ASHC_v3/BrandFunctions.py
ASHC_v3/CommonFunction.py
ASHC_v3/DateFunctions.py
ASHC_v3/Masters.py
ASHC_v3/SaleAndStock.py
ASHC_v3/SaleAndStockExtra.py
ASHC_v3/__init__.py
ASHC_v3/initiateConfig.py
ashc_v3-8.2025.0.dist-info/METADATA
ashc_v3-8.2025.0.dist-info/WHEEL
ashc_v3-8.2025.0.dist-info/licenses/LICENCE.txt
ashc_v3-8.2025.0.dist-info/RECORD
