Metadata-Version: 2.4
Name: ASHC_v3
Version: 8.2025.0
Summary: Some common functions to make work faster
Project-URL: Homepage, https://github.com/sarkar-tanmoy/
Project-URL: Repository, https://github.com/sarkar-tanmoy/
Author-email: Tanmoy Sarkar <tanmoy.apparel@gmail.com>
Maintainer-email: Tanmoy Sarkar <tanmoy.apparel@gmail.com>
License-Expression: MIT AND (Apache-2.0 OR BSD-2-Clause)
License-File: LICENCE.txt
Keywords: ASHC,ashc
Classifier: Development Status :: 5 - Production/Stable
Classifier: Programming Language :: Python :: 3
Requires-Python: >=3.10
Requires-Dist: polars==1.28.1
Requires-Dist: pyside6==6.9.1
Requires-Dist: xlwings==0.33.15
